reapy/__init__.py
reapy/__init__.pyi
reapy/__main__.py
reapy/__main__.pyi
reapy/additional_api.py
reapy/errors.py
reapy/errors.pyi
reapy/py.typed
reapy/reascript_api.py
reapy/reascript_api.pyi
reapy/config/__init__.py
reapy/config/config.py
reapy/config/config.pyi
reapy/config/resource_path.py
reapy/config/shared_library.py
reapy/core/__init__.py
reapy/core/__init__.pyi
reapy/core/audio_accessor.py
reapy/core/audio_accessor.pyi
reapy/core/envelope.py
reapy/core/envelope.pyi
reapy/core/reapy_object.py
reapy/core/reapy_object.pyi
reapy/core/fx/__init__.py
reapy/core/fx/__init__.pyi
reapy/core/fx/fx.py
reapy/core/fx/fx.pyi
reapy/core/fx/fx_param.py
reapy/core/fx/fx_param.pyi
reapy/core/item/__init__.py
reapy/core/item/__init__.pyi
reapy/core/item/item.py
reapy/core/item/item.pyi
reapy/core/item/midi_event.py
reapy/core/item/midi_event.pyi
reapy/core/item/source.py
reapy/core/item/source.pyi
reapy/core/item/take.py
reapy/core/item/take.pyi
reapy/core/project/__init__.py
reapy/core/project/__init__.pyi
reapy/core/project/commands.py
reapy/core/project/commands.pyi
reapy/core/project/marker.py
reapy/core/project/marker.pyi
reapy/core/project/project.py
reapy/core/project/project.pyi
reapy/core/project/region.py
reapy/core/project/region.pyi
reapy/core/project/time_selection.py
reapy/core/project/time_selection.pyi
reapy/core/reaper/__init__.py
reapy/core/reaper/__init__.pyi
reapy/core/reaper/audio.py
reapy/core/reaper/audio.pyi
reapy/core/reaper/defer.py
reapy/core/reaper/defer.pyi
reapy/core/reaper/midi.py
reapy/core/reaper/midi.pyi
reapy/core/reaper/reaper.py
reapy/core/reaper/reaper.pyi
reapy/core/reaper/ui.py
reapy/core/reaper/ui.pyi
reapy/core/track/__init__.py
reapy/core/track/__init__.pyi
reapy/core/track/automation_item.py
reapy/core/track/automation_item.pyi
reapy/core/track/info.py
reapy/core/track/info.pyi
reapy/core/track/send.py
reapy/core/track/send.pyi
reapy/core/track/track.py
reapy/core/track/track.pyi
reapy/core/window/__init__.py
reapy_next-0.10.1.dist-info/licenses/LICENSE.txt
reapy_next-0.10.1.dist-info/METADATA
reapy_next-0.10.1.dist-info/WHEEL
reapy_next-0.10.1.dist-info/top_level.txt
reapy_next-0.10.1.dist-info/RECORD
