Metadata-Version: 2.4
Name: reapy-next
Version: 0.10.1
Summary: Reaper API continue the legacy of RomeoDespres/reapy
Home-page: https://github.com/wiccy46/reapy
Author: Jiajun Yang
Author-email: thejyang@gmail.com
License: MIT
Keywords: automation,api,reaper,audio,music
Classifier: Intended Audience :: Developers
Classifier: Operating System :: OS Independent
Classifier: Programming Language :: Python :: 3
Classifier: Topic :: Software Development :: Libraries :: Python Modules
Classifier: Topic :: System :: Archiving :: Packaging
Requires-Python: >=3.5
License-File: LICENSE.txt
Requires-Dist: setuptools
Requires-Dist: psutil
Requires-Dist: typing_extensions
Dynamic: license-file
